qti2latex.py
qti2latex-0.1.4.dist-info/METADATA
qti2latex-0.1.4.dist-info/WHEEL
qti2latex-0.1.4.dist-info/entry_points.txt
qti2latex-0.1.4.dist-info/top_level.txt
qti2latex-0.1.4.dist-info/RECORD
