Metadata-Version: 2.4
Name: qti2latex
Version: 0.1.4
Summary: Convert QTI (Canvas) to LaTeX exam. Designed to work with text2qti, but should also work with quiz files exported from Canvas.
Author: breed
License-Expression: 0BSD
Classifier: Development Status :: 4 - Beta
Classifier: Environment :: Console
Classifier: Intended Audience :: Education
Classifier: Operating System :: OS Independent
Classifier: Programming Language :: Python
Classifier: Topic :: Education :: Testing
Requires-Python: >=3.6
Requires-Dist: pypandoc
Requires-Dist: click
